ploomber_cloud/__init__.py
ploomber_cloud/_telemetry.py
ploomber_cloud/abc.py
ploomber_cloud/api.py
ploomber_cloud/api_key.py
ploomber_cloud/auth.py
ploomber_cloud/cli.py
ploomber_cloud/client.py
ploomber_cloud/config.py
ploomber_cloud/constants.py
ploomber_cloud/delete.py
ploomber_cloud/deploy.py
ploomber_cloud/examples.py
ploomber_cloud/exceptions.py
ploomber_cloud/file_watcher.py
ploomber_cloud/functions.py
ploomber_cloud/github.py
ploomber_cloud/init.py
ploomber_cloud/io.py
ploomber_cloud/labels.py
ploomber_cloud/logs.py
ploomber_cloud/messages.py
ploomber_cloud/models.py
ploomber_cloud/resources.py
ploomber_cloud/start_stop.py
ploomber_cloud/templates.py
ploomber_cloud/util.py
ploomber_cloud/zip_.py
ploomber_cloud/assets/__init__.py
ploomber_cloud/assets/vllm/Dockerfile
ploomber_cloud/assets/vllm/__init__.py
ploomber_cloud/assets/vllm/requirements.txt
ploomber_cloud/assets/vllm/test-vllm.py
ploomber_cloud/configurations/__init__.py
ploomber_cloud/configurations/community.json
ploomber_cloud/configurations/pro.json
ploomber_cloud/configurations/teams.json
ploomber_cloud-0.4.5.dist-info/METADATA
ploomber_cloud-0.4.5.dist-info/WHEEL
ploomber_cloud-0.4.5.dist-info/entry_points.txt
ploomber_cloud-0.4.5.dist-info/top_level.txt
ploomber_cloud-0.4.5.dist-info/RECORD
