Metadata-Version: 2.4
Name: ploomber-cloud
Version: 0.4.5
Requires-Dist: click
Requires-Dist: requests
Requires-Dist: ploomber-core>=0.2.27
Requires-Dist: python-dotenv
Requires-Dist: cloudpickle==3.0.0
Requires-Dist: watchdog==6.0.0
Provides-Extra: dev
Requires-Dist: pytest; extra == "dev"
Requires-Dist: flake8; extra == "dev"
Requires-Dist: twine; extra == "dev"
Requires-Dist: pkgmt; extra == "dev"
Requires-Dist: ipdb; extra == "dev"
Requires-Dist: ipython; extra == "dev"
Dynamic: provides-extra
Dynamic: requires-dist
